EntityNormalizer/Dictionaries.py
EntityNormalizer/__init__.py
EntityNormalizer/resources/MedDic-CANCER-ADE-JA_202306.csv
EntityNormalizer/resources/MedDic-CANCER-DRUG-JA_202306.csv
EntityNormalizer-0.2.0.dist-info/LICENSE.txt
EntityNormalizer-0.2.0.dist-info/METADATA
EntityNormalizer-0.2.0.dist-info/WHEEL
EntityNormalizer-0.2.0.dist-info/top_level.txt
EntityNormalizer-0.2.0.dist-info/RECORD
