Metadata-Version: 2.1
Name: EntityNormalizer
Version: 0.2.0
Summary: Library for normalizing entities based on a dictionary
Home-page: https://github.com/sociocom/EntityNormalizer
Download-URL: https://github.com/sociocom/EntityNormalizer/archive/refs/tags/0.2.0.tar.gz
Author: Gabriel Herman Bernardim Andrade
License: MIT
License-File: LICENSE.txt
Requires-Dist: pandas
Requires-Dist: rapidfuzz
Requires-Dist: mojimoji
